cpy2py/__init__.py
cpy2py/meta.py
cpy2py/ipyc/__init__.py
cpy2py/ipyc/ipyc_exceptions.py
cpy2py/ipyc/ipyc_fifo.py
cpy2py/ipyc/ipyc_socket.py
cpy2py/kernel/__init__.py
cpy2py/kernel/kernel_async.py
cpy2py/kernel/kernel_core.py
cpy2py/kernel/kernel_exceptions.py
cpy2py/kernel/kernel_multi.py
cpy2py/kernel/kernel_requesthandler.py
cpy2py/kernel/kernel_single.py
cpy2py/kernel/kernel_state.py
cpy2py/proxy/__init__.py
cpy2py/proxy/proxy_func.py
cpy2py/proxy/proxy_instance.py
cpy2py/proxy/proxy_meta.py
cpy2py/proxy/proxy_object.py
cpy2py/proxy/proxy_proxy.py
cpy2py/proxy/proxy_tracker.py
cpy2py/proxy/proxy_twin.py
cpy2py/twinterpreter/__init__.py
cpy2py/twinterpreter/bootstrap.py
cpy2py/twinterpreter/group_state.py
cpy2py/twinterpreter/kernel.py
cpy2py/twinterpreter/kernel_exceptions.py
cpy2py/twinterpreter/kernel_state.py
cpy2py/twinterpreter/twin_def.py
cpy2py/twinterpreter/twin_exceptions.py
cpy2py/twinterpreter/twin_main.py
cpy2py/twinterpreter/twin_master.py
cpy2py/utility/__init__.py
cpy2py/utility/compat.py
cpy2py/utility/enum.py
cpy2py/utility/exceptions.py
cpy2py/utility/proc_tools.py
cpy2py/utility/proxy.py
cpy2py/utility/thread_tools.py
cpy2py/utility/utils.py
cpy2py-0.17.1.dist-info/DESCRIPTION.rst
cpy2py-0.17.1.dist-info/METADATA
cpy2py-0.17.1.dist-info/RECORD
cpy2py-0.17.1.dist-info/WHEEL
cpy2py-0.17.1.dist-info/metadata.json
cpy2py-0.17.1.dist-info/top_level.txt
