Metadata-Version: 2.0
Name: cpy2py
Version: 0.17.1
Summary: Framework for combining different python interpeters
Home-page: https://github.com/maxfischer2781/cpy2py
Author: Max Fischer
Author-email: maxfischer2781@gmail.com
License: Apache V2.0
Keywords: interpreter framework development ipc processing pypy cpython
Platform: Operating System :: OS Independent
Classifier: Development Status :: 4 - Beta
Classifier: Intended Audience :: Developers
Classifier: License :: OSI Approved :: Apache Software License
Classifier: Programming Language :: Python :: 2.6
Classifier: Programming Language :: Python :: 2.7
Classifier: Programming Language :: Python :: 3.3
Classifier: Programming Language :: Python :: 3.4
Classifier: Programming Language :: Python :: 3.5
Classifier: Programming Language :: Python :: Implementation :: CPython
Classifier: Programming Language :: Python :: Implementation :: PyPy
Classifier: Topic :: Software Development :: Interpreters
Classifier: Topic :: Software Development :: Libraries :: Application Frameworks
Classifier: Topic :: Software Development :: Libraries :: Python Modules
Requires-Dist: backports.range
Provides-Extra: coverage
Requires-Dist: coverage; extra == 'coverage'
Provides-Extra: example
Requires-Dist: matplotlib; extra == 'example'
Provides-Extra: profiling
Requires-Dist: vmprof; extra == 'profiling'
